{
  "id": "plQ4Pcul4AMJzkj",
  "unique_key": "https://crawlee.dev/docs/examples/puppeteer-recursive-crawl",
  "order_no": "1738681082923.355103",
  "handled_at": null,
  "request": {
    "url": "https://crawlee.dev/docs/examples/puppeteer-recursive-crawl",
    "method": "GET",
    "headers": {},
    "payload": null,
    "user_data": {
      "__crawlee": {
        "crawlDepth": 2
      }
    },
    "retry_count": 0,
    "no_retry": false,
    "loaded_url": null,
    "handled_at": null,
    "unique_key": "https://crawlee.dev/docs/examples/puppeteer-recursive-crawl",
    "id": "plQ4Pcul4AMJzkj"
  }
}